forum_guard/__init__.py
forum_guard/main.py
forum_guard/prompts.py
forum_guard-2025.12.22075453.dist-info/METADATA
forum_guard-2025.12.22075453.dist-info/WHEEL
forum_guard-2025.12.22075453.dist-info/top_level.txt
forum_guard-2025.12.22075453.dist-info/RECORD
