Metadata-Version: 2.4
Name: forum-guard
Version: 2025.12.22075453
Summary: enables structured and reliable textual interactions in global forums through pattern matching and retries, facilitating high-quality conversations.
Author-email: forum-guard <hi@eugene.plus>
License: MIT
Project-URL: Homepage, https://github.com/chigwell/forum-guard
Requires-Python: >=3.9
Requires-Dist: langchain-llm7>=0.0.0
Requires-Dist: llmatch-messages>=0.0.0
Requires-Dist: langchain-core>=0.3.0
